markdown2.py
markdown2-2.5.4.dist-info/LICENSE.txt
markdown2-2.5.4.dist-info/METADATA
markdown2-2.5.4.dist-info/WHEEL
markdown2-2.5.4.dist-info/entry_points.txt
markdown2-2.5.4.dist-info/top_level.txt
markdown2-2.5.4.dist-info/RECORD
