Metadata-Version: 2.1
Name: markdown2
Version: 2.5.4
Summary: A fast and complete Python implementation of Markdown
Home-page: https://github.com/trentm/python-markdown2
Author: Trent Mick
Author-email: trentm@gmail.com
Maintainer: Trent Mick
Maintainer-email: trentm@gmail.com
License: MIT
Platform: any
Classifier: Development Status :: 5 - Production/Stable
Classifier: Intended Audience :: Developers
Classifier: License :: OSI Approved :: MIT License
Classifier: Programming Language :: Python
Classifier: Programming Language :: Python :: 3
Classifier: Programming Language :: Python :: 3.9
Classifier: Programming Language :: Python :: 3.10
Classifier: Programming Language :: Python :: 3.11
Classifier: Programming Language :: Python :: 3.12
Classifier: Programming Language :: Python :: 3.13
Classifier: Operating System :: OS Independent
Classifier: Topic :: Software Development :: Libraries :: Python Modules
Classifier: Topic :: Software Development :: Documentation
Classifier: Topic :: Text Processing :: Filters
Classifier: Topic :: Text Processing :: Markup :: HTML
Requires-Python: >=3.9, <4
Provides-Extra: code_syntax_highlighting
Provides-Extra: wavedrom
Provides-Extra: latex
Provides-Extra: all
License-File: LICENSE.txt
